my_fastapi_nacos/__init__.py
my_fastapi_nacos/config/__init__.py
my_fastapi_nacos/core/__init__.py
my_fastapi_nacos/core/config.py
my_fastapi_nacos/core/dependencies.py
my_fastapi_nacos/core/discovery.py
my_fastapi_nacos/core/manager.py
my_fastapi_nacos/core/registration.py
my_fastapi_nacos/core/value.py
my_fastapi_nacos/http/__init__.py
my_fastapi_nacos/http/http_client.py
my_fastapi_nacos/models/__init__.py
my_fastapi_nacos/models/config.py
my_fastapi_nacos/models/service.py
my_fastapi_nacos/utils/__init__.py
my_fastapi_nacos/utils/app_config_utils.py
my_fastapi_nacos/utils/env_utils.py
my_fastapi_nacos/utils/exceptions.py
my_fastapi_nacos/utils/ip_utils.py
my_fastapi_nacos/utils/log_utils.py
my_fastapi_nacos-0.1.1.dist-info/licenses/LICENSE
my_fastapi_nacos-0.1.1.dist-info/METADATA
my_fastapi_nacos-0.1.1.dist-info/WHEEL
my_fastapi_nacos-0.1.1.dist-info/top_level.txt
my_fastapi_nacos-0.1.1.dist-info/RECORD
