Metadata-Version: 2.4
Name: my-fastapi-nacos
Version: 0.1.1
Summary: FastAPI Nacos SDK
Author-email: CarlosHuang <dragon_hht@163.com>
Requires-Python: >=3.10
License-File: LICENSE
Requires-Dist: nacos-sdk-python==2.0.9
Requires-Dist: pyyaml>=6.0
Requires-Dist: fastapi>=0.100.0
Requires-Dist: pydantic>=2.0.0
Requires-Dist: pytest>=9.0.2
Requires-Dist: uvicorn>=0.40.0
Requires-Dist: loguru>=0.7.3
Requires-Dist: dotenv>=0.9.9
Requires-Dist: httpx>=0.28.1
Requires-Dist: dataclasses>=0.8
Dynamic: license-file
